LICENSE.txt
MANIFEST.in
README.md
setup.cfg
setup.py
brickowl/__init__.py
brickowl/api.py
brickowl/authhandler.py
brickowl/config.py
brickowl/utils.py
brickowl/constants/constants.py
brickowl/constants/errors.py
brickowl/endpoints/__init__.py
brickowl/endpoints/base.py
brickowl/endpoints/orders.py
brickowl/models/__init__.py
brickowl/models/base.py
brickowl/models/errors.py
brickowl/models/orders.py
python_brickowl_api.egg-info/PKG-INFO
python_brickowl_api.egg-info/SOURCES.txt
python_brickowl_api.egg-info/dependency_links.txt
python_brickowl_api.egg-info/requires.txt
python_brickowl_api.egg-info/top_level.txt