Metadata-Version: 2.1
Name: python-brickowl-api
Version: 0.1.3
Summary: Wrapper for the BrickOwl API (v1)
Home-page: https://github.com/alexanderlhsglobal/python-brickowl-api
Author: Alexander Schillemans
Author-email: alexander.schillemans@lhs.global
License: GPL-3.0-or-later
Download-URL: https://github.com/alexanderlhsglobal/python-brickowl-api/archive/refs/tags/0.1.3.tar.gz
Keywords: brickowl,brick,owl,brick owl,lego,api
Platform: UNKNOWN
Classifier: Development Status :: 3 - Alpha
Classifier: Intended Audience :: Developers
Classifier: Topic :: Software Development :: Build Tools
Classifier: License :: OSI Approved :: GNU General Public License v3 or later (GPLv3+)
Classifier: Programming Language :: Python :: 3.6
License-File: LICENSE.txt
